gen_avr8/__init__.py
gen_avr8/py.typed
gen_avr8/conf/fosc.yaml
gen_avr8/conf/gen_avr8.cfg
gen_avr8/conf/gen_avr8.logo
gen_avr8/conf/gen_avr8_util.cfg
gen_avr8/conf/mcu.yaml
gen_avr8/conf/project_app.yaml
gen_avr8/conf/project_lib.yaml
gen_avr8/conf/template/app/Makefile.template
gen_avr8/conf/template/app/cflags.template
gen_avr8/conf/template/app/csflags.template
gen_avr8/conf/template/app/module.template
gen_avr8/conf/template/app/objects.template
gen_avr8/conf/template/app/ocflags.template
gen_avr8/conf/template/app/odflags.template
gen_avr8/conf/template/app/sources.template
gen_avr8/conf/template/app/subdir.template
gen_avr8/conf/template/app/tools.template
gen_avr8/conf/template/lib/Makefile.template
gen_avr8/conf/template/lib/aflags.template
gen_avr8/conf/template/lib/avr_lib_c.template
gen_avr8/conf/template/lib/avr_lib_h.template
gen_avr8/conf/template/lib/cflags.template
gen_avr8/conf/template/lib/csflags.template
gen_avr8/conf/template/lib/objects.template
gen_avr8/conf/template/lib/ocflags.template
gen_avr8/conf/template/lib/odflags.template
gen_avr8/conf/template/lib/sources.template
gen_avr8/conf/template/lib/subdir.template
gen_avr8/conf/template/lib/tools.template
gen_avr8/pro/__init__.py
gen_avr8/pro/mcu_selector.py
gen_avr8/pro/module_type.py
gen_avr8/pro/osc_selector.py
gen_avr8/pro/read_template.py
gen_avr8/pro/template_dir.py
gen_avr8/pro/template_type.py
gen_avr8/pro/write_template.py
usr/local/bin/gen_avr8_run.py
gen_avr8-2.6.2.dist-info/LICENSE
gen_avr8-2.6.2.dist-info/METADATA
gen_avr8-2.6.2.dist-info/WHEEL
gen_avr8-2.6.2.dist-info/top_level.txt
gen_avr8-2.6.2.dist-info/RECORD
